{
    "name": "team_streaks",
    "description": "This is a sub-function API for tool soccer_data.\nTool description: Broadage Soccer API brings a wide range of data for Soccer in fixtures, livescores, standings and many more. Team, tournament or match, retrieve real time data for any perspective you need. Our Soccer Coverage includes 350+ tournaments from all around the world with in-depth coverage, giving the chance to present the best sports data from users located anywhere. <br>This is a limited version in RapidApi. <a href=\"https://www.broadage.com/signup/api/free?utm_source=rapidapi&utm_medium=click&utm_campaign=soccer_api\" target=”_blank”>Please, click here to start your Free Trial and try the endpoints with live data now!</a>\nAPI description: Provides the streaks(winning, draw, losing...etc.) of both two teams in tournament.\n\nThe data will return for only -+7 days period, so endpoint can be tested with match that its date is in today +- 7 days. You can choose suitable match from Soccer Match List or Fixture endpoints.",
    "parameters": {
        "type": "object",
        "properties": {
            "matchid": {
                "type": "number",
                "description": "The ID of the match for which streak data is to be retrieved.",
                "default": 1452254.0
            }
        },
        "required": [
            "matchid"
        ]
    }
}