{
    "{'country_name': 'Egypt'}": {
        "error": "",
        "response": {
            "name": "Egypt",
            "latitude": "30.044420",
            "longitude": "31.235712",
            "phone_code": "+20",
            "abbreviation": "EGY",
            "capital_city": "Cairo"
        }
    },
    "{'country_name': 'Zimbabwe'}": {
        "error": "",
        "response": {
            "name": "Zimbabwe",
            "latitude": "-19.015438",
            "longitude": "29.154857",
            "phone_code": "+263",
            "abbreviation": "ZWE",
            "capital_city": "Harare"
        }
    },
    "{'country_name': 'Tanzania'}": {
        "error": "",
        "response": {
            "name": "Tanzania",
            "latitude": "-6.369028",
            "longitude": "34.888822",
            "phone_code": "+255",
            "abbreviation": "TZA",
            "capital_city": "Dodoma"
        }
    },
    "{'country_name': 'Algeria'}": {
        "error": "",
        "response": "{'name': 'Algeria', 'latitude': '28.158938', 'longitude': '2.617323', 'phone_code': '+213', 'abbreviation': 'DZA', 'capital_city': 'Algiers'}"
    },
    "{'country_name': 'Kenya'}": {
        "error": "",
        "response": "{'name': 'Kenya', 'latitude': '-0.023559', 'longitude': '37.906193', 'phone_code': '+254', 'abbreviation': 'KEN', 'capital_city': 'Nairobi'}"
    }
}