{
    "{'number': '1729'}": {
        "error": "",
        "response": {
            "text": "the smallest natural number representable in two different ways as a sum of two positive cubes, as Ramanujan stated on the spot",
            "number": 1729,
            "found": true,
            "type": "math"
        }
    },
    "{'number': '7'}": {
        "error": "",
        "response": {
            "text": "the sum of any two opposite sides on a standard six-sided die",
            "number": 7,
            "found": true,
            "type": "math"
        }
    },
    "{'number': '42'}": {
        "error": "",
        "response": {
            "text": "conjectured to be the scaling factor in the leading order term of the \"sixth moment of the Riemann zeta function\"",
            "number": 42,
            "found": true,
            "type": "math"
        }
    },
    "{'number': 'random'}": {
        "error": "",
        "response": {
            "text": "a composite number, having as its factors 2 × 2 × 2 × 2 × 2 × 2 × 3",
            "number": 192,
            "found": true,
            "type": "math"
        }
    },
    "{'number': '1990'}": {
        "error": "",
        "response": {
            "text": "a stella octangula number",
            "number": 1990,
            "found": true,
            "type": "math"
        }
    },
    "{'number': '15', 'fragment': 'true'}": {
        "error": "",
        "response": {
            "text": "a repdigit in binary (1111)",
            "number": 15,
            "found": true,
            "type": "math"
        }
    },
    "{'number': '15'}": {
        "error": "",
        "response": {
            "text": "the 4th discrete semiprime (3.5) and the first member of the (3.q) discrete semiprime family",
            "number": 15,
            "found": true,
            "type": "math"
        }
    },
    "{'number': '1.16973522'}": {
        "error": "",
        "response": "Invalid url"
    },
    "{'number': '1400246702'}": {
        "error": "",
        "response": {
            "text": "a number for which we're missing a fact (submit one to numbersapi at google mail!)",
            "number": 1400246702,
            "found": false,
            "type": "math"
        }
    },
    "{'number': '1234567890'}": {
        "error": "",
        "response": {
            "text": "a number for which we're missing a fact (submit one to numbersapi at google mail!)",
            "number": 1234567890,
            "found": false,
            "type": "math"
        }
    },
    "{'number': '17'}": {
        "error": "",
        "response": {
            "text": "the least random number, according to the Hackers' Jargon File",
            "number": 17,
            "found": true,
            "type": "math"
        }
    },
    "{'number': '50'}": {
        "error": "",
        "response": {
            "text": "the smallest number that can be written as the sum of of 2 squares in 2 ways",
            "number": 50,
            "found": true,
            "type": "math"
        }
    },
    "{'number': '1995'}": {
        "error": "",
        "response": {
            "text": "the number of graphs with 9 vertices with clique number 6",
            "number": 1995,
            "found": true,
            "type": "math"
        }
    },
    "{'number': '12'}": {
        "error": "",
        "response": {
            "text": "a sublime number, a number that has a perfect number of divisors, and the sum of its divisors is also a perfect number",
            "number": 12,
            "found": true,
            "type": "math"
        }
    },
    "{'number': '45'}": {
        "error": "",
        "response": {
            "text": "the sixth positive integer with a prime factorization of the form p2q, with p and q being prime",
            "number": 45,
            "found": true,
            "type": "math"
        }
    },
    "{'number': '2'}": {
        "error": "",
        "response": {
            "text": "a primorial, as well as its own factorial",
            "number": 2,
            "found": true,
            "type": "math"
        }
    },
    "{'number': '6'}": {
        "error": "",
        "response": {
            "text": "the largest of the four all-Harshad numbers",
            "number": 6,
            "found": true,
            "type": "math"
        }
    },
    "{'number': '8'}": {
        "error": "",
        "response": {
            "text": "the dimension of the octonions and is the highest possible dimension of a normed division algebra",
            "number": 8,
            "found": true,
            "type": "math"
        }
    },
    "{'number': '1729', 'json': 'true'}": {
        "error": "",
        "response": {
            "text": "the smallest natural number representable in two different ways as a sum of two positive cubes, as Ramanujan stated on the spot",
            "number": 1729,
            "found": true,
            "type": "math"
        }
    },
    "{'number': '0'}": {
        "error": "",
        "response": {
            "text": "the additive identity",
            "number": 0,
            "found": true,
            "type": "math"
        }
    },
    "{'number': '250'}": {
        "error": "",
        "response": {
            "text": "the smallest multi-digit number so that the sum of the squares of its prime factors equals the sum of the squares of its digits",
            "number": 250,
            "found": true,
            "type": "math"
        }
    },
    "{'number': '23'}": {
        "error": "",
        "response": {
            "text": "the smallest number of integer-sided boxes that tile a box so that no two boxes share a common length",
            "number": 23,
            "found": true,
            "type": "math"
        }
    },
    "{'number': '1990', 'fragment': 'true'}": {
        "error": "",
        "response": {
            "text": "a stella octangula number",
            "number": 1990,
            "found": true,
            "type": "math"
        }
    },
    "{'number': '1990', 'json': 'true'}": {
        "error": "",
        "response": {
            "text": "a stella octangula number",
            "number": 1990,
            "found": true,
            "type": "math"
        }
    },
    "{'number': '30'}": {
        "error": "",
        "response": {
            "text": "a primorial and is the smallest Giuga number",
            "number": 30,
            "found": true,
            "type": "math"
        }
    },
    "{'number': '1991'}": {
        "error": "",
        "response": {
            "text": "an unremarkable number",
            "number": 1991,
            "found": false,
            "type": "math"
        }
    },
    "{'number': '1985'}": {
        "error": "",
        "response": {
            "text": "a boring number",
            "number": 1985,
            "found": false,
            "type": "math"
        }
    },
    "{'number': '13'}": {
        "error": "",
        "response": {
            "text": "the number of Archimedian solids",
            "number": 13,
            "found": true,
            "type": "math"
        }
    },
    "{'number': '87'}": {
        "error": "",
        "response": {
            "text": "the sum of the squares of the first 4 primes",
            "number": 87,
            "found": true,
            "type": "math"
        }
    },
    "{'number': '17', 'json': 'true'}": {
        "error": "",
        "response": {
            "text": "the 7th prime number",
            "number": 17,
            "found": true,
            "type": "math"
        }
    },
    "{'number': '73'}": {
        "error": "",
        "response": {
            "text": "the only prime repunit in base 8 (1118)",
            "number": 73,
            "found": true,
            "type": "math"
        }
    },
    "{'number': '29'}": {
        "error": "",
        "response": {
            "text": "a Perrin number, preceded in the sequence by 12, 17, 22",
            "number": 29,
            "found": true,
            "type": "math"
        }
    },
    "{'number': '94'}": {
        "error": "",
        "response": {
            "text": "the twenty-ninth distinct semiprime and the fourteenth of the form (2.q)",
            "number": 94,
            "found": true,
            "type": "math"
        }
    },
    "{'number': '99'}": {
        "error": "",
        "response": {
            "text": "the ninth repdigit, a palindromic number and a Kaprekar number",
            "number": 99,
            "found": true,
            "type": "math"
        }
    },
    "{'number': '5'}": {
        "error": "",
        "response": {
            "text": "also the number of Platonic solids",
            "number": 5,
            "found": true,
            "type": "math"
        }
    },
    "{'number': '2000'}": {
        "error": "",
        "response": {
            "text": "an unremarkable number",
            "number": 2000,
            "found": false,
            "type": "math"
        }
    },
    "{'number': '237'}": {
        "error": "",
        "response": {
            "text": "a composite number, with its divisors being 2, 5, 10, 23, 46, and 115",
            "number": 237,
            "found": true,
            "type": "math"
        }
    },
    "{'number': '88'}": {
        "error": "",
        "response": {
            "text": "one of only 2 numbers known whose square has no isolated digits",
            "number": 88,
            "found": true,
            "type": "math"
        }
    },
    "{'number': '60'}": {
        "error": "",
        "response": {
            "text": "the smallest number divisible by 1 through 6",
            "number": 60,
            "found": true,
            "type": "math"
        }
    },
    "{'number': '987'}": {
        "error": "",
        "response": {
            "text": "the 16^{th} Fibonacci number",
            "number": 987,
            "found": true,
            "type": "math"
        }
    },
    "{'number': '1234'}": {
        "error": "",
        "response": {
            "text": "the smallest 4-digit number with increasing digits",
            "number": 1234,
            "found": true,
            "type": "math"
        }
    },
    "{'number': '555'}": {
        "error": "",
        "response": {
            "text": "an unremarkable number",
            "number": 555,
            "found": false,
            "type": "math"
        }
    },
    "{'number': '365'}": {
        "error": "",
        "response": {
            "text": "the smallest number that can be written as a sum of consecutive squares in more than 1 way",
            "number": 365,
            "found": true,
            "type": "math"
        }
    },
    "{'number': '10'}": {
        "error": "",
        "response": {
            "text": "the smallest number whose status as a possible friendly number is unknown",
            "number": 10,
            "found": true,
            "type": "math"
        }
    },
    "{'number': '1'}": {
        "error": "",
        "response": {
            "text": "the first figurate number of every kind, such as triangular number, pentagonal number and centered hexagonal number, to name just a few",
            "number": 1,
            "found": true,
            "type": "math"
        }
    },
    "{'number': '3'}": {
        "error": "",
        "response": {
            "text": "the fourth open meandric number",
            "number": 3,
            "found": true,
            "type": "math"
        }
    },
    "{'number': '92'}": {
        "error": "",
        "response": {
            "text": "the number of different arrangements of 8 non-attacking queens on an 8×8 chessboard",
            "number": 92,
            "found": true,
            "type": "math"
        }
    },
    "{'number': '1492'}": {
        "error": "",
        "response": {
            "text": "the number of lines passing through at least 2 points of an 9×9 grid of points",
            "number": 1492,
            "found": true,
            "type": "math"
        }
    },
    "{'number': '27'}": {
        "error": "",
        "response": {
            "text": "the largest number that is the sum of the digits of its cube",
            "number": 27,
            "found": true,
            "type": "math"
        }
    },
    "{'number': '1989'}": {
        "error": "",
        "response": {
            "text": "a boring number",
            "number": 1989,
            "found": false,
            "type": "math"
        }
    },
    "{'number': '24'}": {
        "error": "",
        "response": {
            "text": "a highly composite number, having more divisors than any smaller number",
            "number": 24,
            "found": true,
            "type": "math"
        }
    },
    "{'number': '1992'}": {
        "error": "",
        "response": {
            "text": "a boring number",
            "number": 1992,
            "found": false,
            "type": "math"
        }
    },
    "{'number': '1995', 'json': 'true'}": {
        "error": "",
        "response": {
            "text": "the number of graphs with 9 vertices with clique number 6",
            "number": 1995,
            "found": true,
            "type": "math"
        }
    },
    "{'number': '291'}": {
        "error": "",
        "response": {
            "text": "the largest number that is not the sum of distinct non-trivial powers",
            "number": 291,
            "found": true,
            "type": "math"
        }
    },
    "{'number': '46'}": {
        "error": "",
        "response": {
            "text": "a Wedderburn-Etherington number, an enneagonal number and a centered triangular number",
            "number": 46,
            "found": true,
            "type": "math"
        }
    },
    "{'number': '182'}": {
        "error": "",
        "response": {
            "text": "a sphenic number, the product of three prime factors",
            "number": 182,
            "found": true,
            "type": "math"
        }
    },
    "{'number': '55'}": {
        "error": "",
        "response": {
            "text": "a semiprime, being the product of 5 and 11 and it is the 2nd member of the (5.q) semiprime family",
            "number": 55,
            "found": true,
            "type": "math"
        }
    },
    "{'number': '9'}": {
        "error": "",
        "response": {
            "text": "the sum of the digits of 41 is 5, and 41-5 = 36",
            "number": 9,
            "found": true,
            "type": "math"
        }
    },
    "{'number': '23', 'fragment': 'true'}": {
        "error": "",
        "response": {
            "text": "the first prime P for which unique factorization of cyclotomic integers based on the Pth root of unity breaks down",
            "number": 23,
            "found": true,
            "type": "math"
        }
    },
    "{'number': '256', 'json': 'true'}": {
        "error": "",
        "response": {
            "text": "an area code in Alabama",
            "number": 256,
            "found": true,
            "type": "math"
        }
    },
    "{'number': '42', 'json': 'true'}": {
        "error": "",
        "response": {
            "text": "the third pentadecagonal number",
            "number": 42,
            "found": true,
            "type": "math"
        }
    },
    "{'number': '7', 'json': 'true'}": {
        "error": "",
        "response": {
            "text": "the sum of any two opposite sides on a standard six-sided die",
            "number": 7,
            "found": true,
            "type": "math"
        }
    },
    "{'number': '166'}": {
        "error": "",
        "response": {
            "text": "the number of monotone Boolean functions of 4 variables",
            "number": 166,
            "found": true,
            "type": "math"
        }
    },
    "{'number': '4'}": {
        "error": "",
        "response": {
            "text": "the smallest composite number that is equal to the sum of its prime factors",
            "number": 4,
            "found": true,
            "type": "math"
        }
    },
    "{'number': '1998', 'json': 'true'}": {
        "error": "",
        "response": {
            "text": "the largest number that is the sum of its digits and the cube of its digits",
            "number": 1998,
            "found": true,
            "type": "math"
        }
    },
    "{'number': '7', 'fragment': 'true'}": {
        "error": "",
        "response": {
            "text": "the only dimension, besides the familiar 3, in which a vector cross product can be defined",
            "number": 7,
            "found": true,
            "type": "math"
        }
    },
    "{'number': '69'}": {
        "error": "",
        "response": {
            "text": "a value of n where n^{2} and n^{3} together contain each digit once",
            "number": 69,
            "found": true,
            "type": "math"
        }
    },
    "{'number': '192'}": {
        "error": "",
        "response": {
            "text": "a composite number, having as its factors 2 × 2 × 2 × 2 × 2 × 2 × 3",
            "number": 192,
            "found": true,
            "type": "math"
        }
    },
    "{'number': '192', 'fragment': 'true'}": {
        "error": "",
        "response": {
            "text": "a composite number, having as its factors 2 × 2 × 2 × 2 × 2 × 2 × 3",
            "number": 192,
            "found": true,
            "type": "math"
        }
    },
    "{'number': '45', 'json': 'true'}": {
        "error": "",
        "response": {
            "text": "a triangular number, a hexagonal and 16-gonal number, a Kaprekar number, and a Harshad number",
            "number": 45,
            "found": true,
            "type": "math"
        }
    },
    "{'number': '363'}": {
        "error": "",
        "response": {
            "text": "a perfect totient number",
            "number": 363,
            "found": true,
            "type": "math"
        }
    },
    "{'number': '456'}": {
        "error": "",
        "response": {
            "text": "the number of tournaments with 7 vertices",
            "number": 456,
            "found": true,
            "type": "math"
        }
    },
    "{'number': '2021'}": {
        "error": "",
        "response": {
            "text": "the product of two consecutive primes",
            "number": 2021,
            "found": true,
            "type": "math"
        }
    },
    "{'number': '32'}": {
        "error": "",
        "response": {
            "text": "the smallest non-trivial 5^{th} power",
            "number": 32,
            "found": true,
            "type": "math"
        }
    },
    "{'number': '2468'}": {
        "error": "",
        "response": {
            "text": "a number for which we're missing a fact (submit one to numbersapi at google mail!)",
            "number": 2468,
            "found": false,
            "type": "math"
        }
    },
    "{'number': 'random', 'json': 'true'}": {
        "error": "",
        "response": {
            "text": "the smallest number with 14 divisors",
            "number": 192,
            "found": true,
            "type": "math"
        }
    },
    "{'number': '1000'}": {
        "error": "",
        "response": {
            "text": "an unremarkable number",
            "number": 1000,
            "found": false,
            "type": "math"
        }
    },
    "{'number': '82'}": {
        "error": "",
        "response": {
            "text": "the twenty-third biprime and the twelfth of the form (2.q)",
            "number": 82,
            "found": true,
            "type": "math"
        }
    },
    "{'number': '82', 'fragment': 'true'}": {
        "error": "",
        "response": {
            "text": "the twenty-third biprime and the twelfth of the form (2.q)",
            "number": 82,
            "found": true,
            "type": "math"
        }
    },
    "{'number': '1889'}": {
        "error": "",
        "response": {
            "text": "the smallest prime so that it and the next 4 primes are all equal to 5 (mod 6)",
            "number": 1889,
            "found": true,
            "type": "math"
        }
    },
    "{'number': '1776'}": {
        "error": "",
        "response": {
            "text": "a number for which we're missing a fact (submit one to numbersapi at google mail!)",
            "number": 1776,
            "found": false,
            "type": "math"
        }
    },
    "{'number': '9', 'fragment': 'true'}": {
        "error": "",
        "response": {
            "text": "the highest single-digit number in the decimal system",
            "number": 9,
            "found": true,
            "type": "math"
        }
    },
    "{'number': '80'}": {
        "error": "",
        "response": {
            "text": "the smallest number n where n and n+1 are both products of 4 or more primes",
            "number": 80,
            "found": true,
            "type": "math"
        }
    },
    "{'number': '1732'}": {
        "error": "",
        "response": {
            "text": "a number for which we're missing a fact (submit one to numbersapi at google mail!)",
            "number": 1732,
            "found": false,
            "type": "math"
        }
    },
    "{'number': '1230'}": {
        "error": "",
        "response": {
            "text": "the number of square-free graphs with 9 vertices",
            "number": 1230,
            "found": true,
            "type": "math"
        }
    },
    "{'number': '621', 'json': 'true'}": {
        "error": "",
        "response": {
            "text": "the number of ways to 9-color the faces of a tetrahedron",
            "number": 621,
            "found": true,
            "type": "math"
        }
    },
    "{'number': '123'}": {
        "error": "",
        "response": {
            "text": "the 10^{th} Lucas number",
            "number": 123,
            "found": true,
            "type": "math"
        }
    },
    "{'number': '21'}": {
        "error": "",
        "response": {
            "text": "a repdigit in base 4 (111)",
            "number": 21,
            "found": true,
            "type": "math"
        }
    },
    "{'number': '173'}": {
        "error": "",
        "response": {
            "text": "an Eisenstein prime with no imaginary part",
            "number": 173,
            "found": true,
            "type": "math"
        }
    },
    "{'number': '28'}": {
        "error": "",
        "response": {
            "text": "in the Padovan sequence, preceded by the terms 12, 16, 21 (it is the sum of the first two of these)",
            "number": 28,
            "found": true,
            "type": "math"
        }
    },
    "{'number': '16'}": {
        "error": "",
        "response": {
            "text": "the base of the hexadecimal number system, which is used extensively in computer science",
            "number": 16,
            "found": true,
            "type": "math"
        }
    },
    "{'number': '621'}": {
        "error": "",
        "response": {
            "text": "the number of ways to 9-color the faces of a tetrahedron",
            "number": 621,
            "found": true,
            "type": "math"
        }
    },
    "{'number': '2019'}": {
        "error": "",
        "response": {
            "text": "an unremarkable number",
            "number": 2019,
            "found": false,
            "type": "math"
        }
    },
    "{'number': '58'}": {
        "error": "",
        "response": {
            "text": "the number of commutative semigroups of order 4",
            "number": 58,
            "found": true,
            "type": "math"
        }
    },
    "{'number': '14'}": {
        "error": "",
        "response": {
            "text": "the 3rd discrete semiprime ( 2 ",
            "number": 14,
            "found": true,
            "type": "math"
        }
    },
    "{'number': '100'}": {
        "error": "",
        "response": {
            "text": "a Harshad number in base 10, and also in base 4, and in that base it is a self-descriptive number",
            "number": 100,
            "found": true,
            "type": "math"
        }
    },
    "{'number': '200'}": {
        "error": "",
        "response": {
            "text": "the smallest number which can not be made prime by changing one of its digits",
            "number": 200,
            "found": true,
            "type": "math"
        }
    },
    "{'number': '300'}": {
        "error": "",
        "response": {
            "text": "the largest possible score in bowling",
            "number": 300,
            "found": true,
            "type": "math"
        }
    },
    "{'number': '1500'}": {
        "error": "",
        "response": {
            "text": "(5+1) × (5+5) × (5+0) × (5+0)",
            "number": 1500,
            "found": true,
            "type": "math"
        }
    },
    "{'number': '2022'}": {
        "error": "",
        "response": {
            "text": "a number for which we're missing a fact (submit one to numbersapi at google mail!)",
            "number": 2022,
            "found": false,
            "type": "math"
        }
    },
    "{'number': '307'}": {
        "error": "",
        "response": {
            "text": "a non-palindrome with a palindromic square",
            "number": 307,
            "found": true,
            "type": "math"
        }
    },
    "{'number': '75'}": {
        "error": "",
        "response": {
            "text": "the number of orderings of 4 objects with ties allowed",
            "number": 75,
            "found": true,
            "type": "math"
        }
    },
    "{'number': '2023'}": {
        "error": "",
        "response": {
            "text": "a boring number",
            "number": 2023,
            "found": false,
            "type": "math"
        }
    },
    "{'number': '149', 'json': 'true'}": {
        "error": "",
        "response": {
            "text": "a strictly non-palindromic number, meaning that it is not palindromic in any base from binary to base 147",
            "number": 149,
            "found": true,
            "type": "math"
        }
    },
    "{'number': '156'}": {
        "error": "",
        "response": {
            "text": "the number of graphs with 6 vertices",
            "number": 156,
            "found": true,
            "type": "math"
        }
    },
    "{'number': '500'}": {
        "error": "",
        "response": {
            "text": "the number of planar partitions of 10",
            "number": 500,
            "found": true,
            "type": "math"
        }
    },
    "{'number': '9876'}": {
        "error": "",
        "response": {
            "text": "the largest 4-digit number with different digits",
            "number": 9876,
            "found": true,
            "type": "math"
        }
    },
    "{'number': '10000'}": {
        "error": "",
        "response": {
            "text": "an unremarkable number",
            "number": 10000,
            "found": false,
            "type": "math"
        }
    },
    "{'number': '1982'}": {
        "error": "",
        "response": {
            "text": "a boring number",
            "number": 1982,
            "found": false,
            "type": "math"
        }
    },
    "{'number': '620'}": {
        "error": "",
        "response": {
            "text": "the number of sided 7-hexes",
            "number": 620,
            "found": true,
            "type": "math"
        }
    },
    "{'number': '4321'}": {
        "error": "",
        "response": {
            "text": "an unremarkable number",
            "number": 4321,
            "found": false,
            "type": "math"
        }
    },
    "{'number': '432'}": {
        "error": "",
        "response": {
            "text": "an uninteresting number",
            "number": 432,
            "found": false,
            "type": "math"
        }
    },
    "{'number': '5280'}": {
        "error": "",
        "response": {
            "text": "the number of feet in a mile",
            "number": 5280,
            "found": true,
            "type": "math"
        }
    },
    "{'number': '12345'}": {
        "error": "",
        "response": {
            "text": "a number for which we're missing a fact (submit one to numbersapi at google mail!)",
            "number": 12345,
            "found": false,
            "type": "math"
        }
    },
    "{'number': '25'}": {
        "error": "",
        "response": {
            "text": "a square number, being 5² = 5 × 5",
            "number": 25,
            "found": true,
            "type": "math"
        }
    },
    "{'number': '1972'}": {
        "error": "",
        "response": {
            "text": "an uninteresting number",
            "number": 1972,
            "found": false,
            "type": "math"
        }
    },
    "{'number': '146'}": {
        "error": "",
        "response": {
            "text": "a repdigit in base 8 (222)",
            "number": 146,
            "found": true,
            "type": "math"
        }
    },
    "{'number': 'random', 'fragment': 'true'}": {
        "error": "",
        "response": {
            "text": "the number of ordered sequences of coins totaling 30 cents",
            "number": 4237,
            "found": true,
            "type": "math"
        }
    },
    "{'number': '135'}": {
        "error": "",
        "response": {
            "text": "1^{1} + 3^{2} + 5^{3}",
            "number": 135,
            "found": true,
            "type": "math"
        }
    },
    "{'number': '21', 'fragment': 'true'}": {
        "error": "",
        "response": {
            "text": "a repdigit in base 4 (111)",
            "number": 21,
            "found": true,
            "type": "math"
        }
    },
    "{'number': '12', 'fragment': 'true'}": {
        "error": "",
        "response": {
            "text": "the smallest abundant number",
            "number": 12,
            "found": true,
            "type": "math"
        }
    },
    "{'number': '999'}": {
        "error": "",
        "response": {
            "text": "an unremarkable number",
            "number": 999,
            "found": false,
            "type": "math"
        }
    },
    "{'number': '0.9160499999999999'}": {
        "error": "",
        "response": "Invalid url"
    },
    "{'number': '5', 'fragment': 'true'}": {
        "error": "",
        "response": {
            "text": "the third prime number",
            "number": 5,
            "found": true,
            "type": "math"
        }
    },
    "{'number': '1729', 'fragment': 'true'}": {
        "error": "",
        "response": {
            "text": "the smallest natural number representable in two different ways as a sum of two positive cubes, as Ramanujan stated on the spot",
            "number": 1729,
            "found": true,
            "type": "math"
        }
    },
    "{'number': '276'}": {
        "error": "",
        "response": {
            "text": "the sum of twelve consecutive prime numbers (5 + 7 + 11 + 13 + 17 + 19 + 23 + 29 + 31 + 37 + 41 + 43)",
            "number": 276,
            "found": true,
            "type": "math"
        }
    },
    "{'number': '42', 'fragment': 'true'}": {
        "error": "",
        "response": {
            "text": "the 5^{th} Catalan number",
            "number": 42,
            "found": true,
            "type": "math"
        }
    },
    "{'number': '37'}": {
        "error": "",
        "response": {
            "text": "a prime number, the fifth lucky prime, the first irregular prime, the third unique prime and the third cuban prime of the form",
            "number": 37,
            "found": true,
            "type": "math"
        }
    },
    "{'number': '1492', 'fragment': 'true'}": {
        "error": "",
        "response": {
            "text": "the number of lines passing through at least 2 points of an 9×9 grid of points",
            "number": 1492,
            "found": true,
            "type": "math"
        }
    },
    "{'number': '5', 'json': 'true'}": {
        "error": "",
        "response": {
            "text": "also the number of Platonic solids",
            "number": 5,
            "found": true,
            "type": "math"
        }
    },
    "{'number': '314159'}": {
        "error": "",
        "response": {
            "text": "a number for which we're missing a fact (submit one to numbersapi at google mail!)",
            "number": 314159,
            "found": false,
            "type": "math"
        }
    },
    "{'number': '0.91605'}": {
        "error": "",
        "response": "Invalid url"
    },
    "{'number': '67890'}": {
        "error": "",
        "response": {
            "text": "a number for which we're missing a fact (submit one to numbersapi at google mail!)",
            "number": 67890,
            "found": false,
            "type": "math"
        }
    },
    "{'number': '12373495'}": {
        "error": "",
        "response": {
            "text": "an unremarkable number",
            "number": 12373495,
            "found": false,
            "type": "math"
        }
    },
    "{'number': '12373491'}": {
        "error": "",
        "response": {
            "text": "an unremarkable number",
            "number": 12373491,
            "found": false,
            "type": "math"
        }
    },
    "{'number': '2460'}": {
        "error": "",
        "response": {
            "text": "a number for which we're missing a fact (submit one to numbersapi at google mail!)",
            "number": 2460,
            "found": false,
            "type": "math"
        }
    },
    "{'number': '1642'}": {
        "error": "",
        "response": {
            "text": "a number for which we're missing a fact (submit one to numbersapi at google mail!)",
            "number": 1642,
            "found": false,
            "type": "math"
        }
    },
    "{'number': '20'}": {
        "error": "",
        "response": {
            "text": "the 4th composite number in the 7-aliquot tree",
            "number": 20,
            "found": true,
            "type": "math"
        }
    },
    "{'number': '22'}": {
        "error": "",
        "response": {
            "text": "the number of partitions of 8",
            "number": 22,
            "found": true,
            "type": "math"
        }
    },
    "{'number': '6363'}": {
        "error": "",
        "response": {
            "text": "a number for which we're missing a fact (submit one to numbersapi at google mail!)",
            "number": 6363,
            "found": false,
            "type": "math"
        }
    },
    "{'number': '5678'}": {
        "error": "",
        "response": {
            "text": "an unremarkable number",
            "number": 5678,
            "found": false,
            "type": "math"
        }
    },
    "{'number': '1957'}": {
        "error": "",
        "response": {
            "text": "the number of permutations of some subset of 6 elements",
            "number": 1957,
            "found": true,
            "type": "math"
        }
    },
    "{'number': '72'}": {
        "error": "",
        "response": {
            "text": "the maximum number of spheres that can touch another sphere in a lattice packing in 6 dimensions",
            "number": 72,
            "found": true,
            "type": "math"
        }
    },
    "{'number': '2465'}": {
        "error": "",
        "response": {
            "text": "an uninteresting number",
            "number": 2465,
            "found": false,
            "type": "math"
        }
    },
    "{'number': '1230', 'fragment': 'true'}": {
        "error": "",
        "response": {
            "text": "the number of square-free graphs with 9 vertices",
            "number": 1230,
            "found": true,
            "type": "math"
        }
    },
    "{'number': '246', 'fragment': 'true'}": {
        "error": "",
        "response": {
            "text": "_{9}C_{2} + _{9}C_{4} + _{9}C_{6}",
            "number": 246,
            "found": true,
            "type": "math"
        }
    },
    "{'number': '13', 'json': 'true'}": {
        "error": "",
        "response": {
            "text": "the number of Archimedian solids",
            "number": 13,
            "found": true,
            "type": "math"
        }
    },
    "{'number': '328'}": {
        "error": "",
        "response": {
            "text": "a number for which we're missing a fact (submit one to numbersapi at google mail!)",
            "number": 328,
            "found": false,
            "type": "math"
        }
    },
    "{'number': '1789'}": {
        "error": "",
        "response": {
            "text": "the smallest number with the property that its first 4 multiples contain the digit 7",
            "number": 1789,
            "found": true,
            "type": "math"
        }
    },
    "{'number': '444'}": {
        "error": "",
        "response": {
            "text": "the largest known n for which there is a unique integer solution to a_{1}+ ... +a_{n} = (a_{1})...(a_{n})",
            "number": 444,
            "found": true,
            "type": "math"
        }
    },
    "{'number': '57'}": {
        "error": "",
        "response": {
            "text": "the sixteenth discrete semiprime and the sixth in the (3.q) family",
            "number": 57,
            "found": true,
            "type": "math"
        }
    },
    "{'number': '105'}": {
        "error": "",
        "response": {
            "text": "the largest number n known with the property that n - 2^{k} is prime for k>1",
            "number": 105,
            "found": true,
            "type": "math"
        }
    },
    "{'number': '789'}": {
        "error": "",
        "response": {
            "text": "an unremarkable number",
            "number": 789,
            "found": false,
            "type": "math"
        }
    },
    "{'number': '64'}": {
        "error": "",
        "response": {
            "text": "the smallest number with 7 divisors",
            "number": 64,
            "found": true,
            "type": "math"
        }
    },
    "{'number': '314'}": {
        "error": "",
        "response": {
            "text": "the smallest number that can be written as the sum of of 3 positive distinct squares in 6 ways",
            "number": 314,
            "found": true,
            "type": "math"
        }
    },
    "{'number': '41'}": {
        "error": "",
        "response": {
            "text": "a centered square number",
            "number": 41,
            "found": true,
            "type": "math"
        }
    },
    "{'number': '43'}": {
        "error": "",
        "response": {
            "text": "the number of sided 7-iamonds",
            "number": 43,
            "found": true,
            "type": "math"
        }
    },
    "{'number': '324'}": {
        "error": "",
        "response": {
            "text": "the largest possible product of positive integers with sum 16",
            "number": 324,
            "found": true,
            "type": "math"
        }
    },
    "{'number': '36'}": {
        "error": "",
        "response": {
            "text": "both the square of 6 and a triangular number, making it a square triangular number",
            "number": 36,
            "found": true,
            "type": "math"
        }
    },
    "{'number': '14', 'fragment': 'true'}": {
        "error": "",
        "response": {
            "text": "itself the Aliquot sum of two numbers; the discrete semiprime 22, and the square number 196",
            "number": 14,
            "found": true,
            "type": "math"
        }
    },
    "{'number': '3.4514'}": {
        "error": "",
        "response": "Invalid url"
    },
    "{'number': '1728'}": {
        "error": "",
        "response": {
            "text": "a boring number",
            "number": 1728,
            "found": false,
            "type": "math"
        }
    },
    "{'number': '369'}": {
        "error": "",
        "response": {
            "text": "the number of octominoes",
            "number": 369,
            "found": true,
            "type": "math"
        }
    },
    "{'number': '1946'}": {
        "error": "",
        "response": {
            "text": "a boring number",
            "number": 1946,
            "found": false,
            "type": "math"
        }
    },
    "{'number': '1326'}": {
        "error": "",
        "response": {
            "text": "a boring number",
            "number": 1326,
            "found": false,
            "type": "math"
        }
    },
    "{'number': '1912'}": {
        "error": "",
        "response": {
            "text": "a structured octagonal anti-diamond number",
            "number": 1912,
            "found": true,
            "type": "math"
        }
    },
    "{'number': '419'}": {
        "error": "",
        "response": {
            "text": "the number of ways to divide a 6×6 grid of points into two sets using a straight line",
            "number": 419,
            "found": true,
            "type": "math"
        }
    },
    "{'number': '302127'}": {
        "error": "",
        "response": {
            "text": "an uninteresting number",
            "number": 302127,
            "found": false,
            "type": "math"
        }
    },
    "{'number': '84'}": {
        "error": "",
        "response": {
            "text": "also the lim sup of the largest finite subgroup of the mapping class group of a genus g surface divided by g",
            "number": 84,
            "found": true,
            "type": "math"
        }
    },
    "{'number': '123456789'}": {
        "error": "",
        "response": {
            "text": "an uninteresting number",
            "number": 123456789,
            "found": false,
            "type": "math"
        }
    },
    "{'number': '987654321'}": {
        "error": "",
        "response": {
            "text": "a number for which we're missing a fact (submit one to numbersapi at google mail!)",
            "number": 987654321,
            "found": false,
            "type": "math"
        }
    },
    "{'number': '1950'}": {
        "error": "",
        "response": {
            "text": "a boring number",
            "number": 1950,
            "found": false,
            "type": "math"
        }
    },
    "{'number': '9173'}": {
        "error": "",
        "response": {
            "text": "an uninteresting number",
            "number": 9173,
            "found": false,
            "type": "math"
        }
    },
    "{'number': '256'}": {
        "error": "",
        "response": {
            "text": "the split-screen level in Pacman, which results from the use of a single byte to store the internal level counter",
            "number": 256,
            "found": true,
            "type": "math"
        }
    },
    "{'number': '18'}": {
        "error": "",
        "response": {
            "text": "a composite number, its proper divisors being 1, 2, 3, 6 and 9",
            "number": 18,
            "found": true,
            "type": "math"
        }
    },
    "{'number': '1111'}": {
        "error": "",
        "response": {
            "text": "an uninteresting number",
            "number": 1111,
            "found": false,
            "type": "math"
        }
    },
    "{'number': '735'}": {
        "error": "",
        "response": {
            "text": "the smallest number that is the concatenation of its distinct prime factors",
            "number": 735,
            "found": true,
            "type": "math"
        }
    },
    "{'number': '2020'}": {
        "error": "",
        "response": {
            "text": "an autobiographical number",
            "number": 2020,
            "found": true,
            "type": "math"
        }
    },
    "{'number': '399300322'}": {
        "error": "",
        "response": {
            "text": "a number for which we're missing a fact (submit one to numbersapi at google mail!)",
            "number": 399300322,
            "found": false,
            "type": "math"
        }
    },
    "{'number': '174'}": {
        "error": "",
        "response": {
            "text": "an abundant number with the abundance of 12",
            "number": 174,
            "found": true,
            "type": "math"
        }
    },
    "{'number': '567'}": {
        "error": "",
        "response": {
            "text": "a boring number",
            "number": 567,
            "found": false,
            "type": "math"
        }
    },
    "{'number': '9999'}": {
        "error": "",
        "response": {
            "text": "an uninteresting number",
            "number": 9999,
            "found": false,
            "type": "math"
        }
    },
    "{'number': '56'}": {
        "error": "",
        "response": {
            "text": "the sum of the first six triangular numbers (making it a tetrahedral number), as well as the sum of six consecutive primes (3 + 5 + 7 + 11 + 13 + 17)",
            "number": 56,
            "found": true,
            "type": "math"
        }
    },
    "{'number': '101'}": {
        "error": "",
        "response": {
            "text": "the 26th prime number and a palindromic number (and so a palindromic prime)",
            "number": 101,
            "found": true,
            "type": "math"
        }
    },
    "{'number': '911'}": {
        "error": "",
        "response": {
            "text": "the American emergency number",
            "number": 911,
            "found": true,
            "type": "math"
        }
    },
    "{'number': '34'}": {
        "error": "",
        "response": {
            "text": "the ninth Fibonacci number and a companion Pell number",
            "number": 34,
            "found": true,
            "type": "math"
        }
    },
    "{'number': '249'}": {
        "error": "",
        "response": {
            "text": "the index of a prime Woodall number",
            "number": 249,
            "found": true,
            "type": "math"
        }
    },
    "{'number': '907'}": {
        "error": "",
        "response": {
            "text": "the largest n so that Q(vn) has class number 3",
            "number": 907,
            "found": true,
            "type": "math"
        }
    },
    "{'number': '531'}": {
        "error": "",
        "response": {
            "text": "the smallest number with the property that its first 4 multiples contain the digit 1",
            "number": 531,
            "found": true,
            "type": "math"
        }
    },
    "{'number': '1987'}": {
        "error": "",
        "response": {
            "text": "a boring number",
            "number": 1987,
            "found": false,
            "type": "math"
        }
    },
    "{'number': '6', 'fragment': 'true'}": {
        "error": "",
        "response": {
            "text": "the only number that is both the sum and the product of three consecutive positive numbers",
            "number": 6,
            "found": true,
            "type": "math"
        }
    },
    "{'number': '68'}": {
        "error": "",
        "response": {
            "text": "the 2-digit string that appears latest in the decimal expansion of p",
            "number": 68,
            "found": true,
            "type": "math"
        }
    },
    "{'number': '98'}": {
        "error": "",
        "response": {
            "text": "the smallest number with the property that its first 5 multiples contain the digit 9",
            "number": 98,
            "found": true,
            "type": "math"
        }
    },
    "{'number': '294'}": {
        "error": "",
        "response": {
            "text": "the number of planar 2-connected graphs with 7 vertices",
            "number": 294,
            "found": true,
            "type": "math"
        }
    },
    "{'number': '74'}": {
        "error": "",
        "response": {
            "text": "the number of different non-Hamiltonian polyhedra with a minimum number of vertices",
            "number": 74,
            "found": true,
            "type": "math"
        }
    },
    "{'number': '1066'}": {
        "error": "",
        "response": {
            "text": "a value of n for which 2f(n) = f(n+1)",
            "number": 1066,
            "found": true,
            "type": "math"
        }
    },
    "{'number': '5324'}": {
        "error": "",
        "response": {
            "text": "the number of binary cube-free words of length 20",
            "number": 5324,
            "found": true,
            "type": "math"
        }
    },
    "{'number': '305'}": {
        "error": "",
        "response": {
            "text": "an hexagonal prism number",
            "number": 305,
            "found": true,
            "type": "math"
        }
    },
    "{'number': '186'}": {
        "error": "",
        "response": {
            "text": "a sphenic number, so the Möbius function returns -1 (and the Mertens function returns -4)",
            "number": 186,
            "found": true,
            "type": "math"
        }
    },
    "{'number': '170'}": {
        "error": "",
        "response": {
            "text": "the smallest n for which φ(n) and σ(n) are both square(64 and 324 respectively)",
            "number": 170,
            "found": true,
            "type": "math"
        }
    },
    "{'number': '1395'}": {
        "error": "",
        "response": {
            "text": "an uninteresting number",
            "number": 1395,
            "found": false,
            "type": "math"
        }
    },
    "{'number': '1731'}": {
        "error": "",
        "response": {
            "text": "the sum of the squares of 3 consecutive primes",
            "number": 1731,
            "found": true,
            "type": "math"
        }
    },
    "{'number': '19'}": {
        "error": "",
        "response": {
            "text": "a centered triangular number, centered hexagonal number and a Heegner number",
            "number": 19,
            "found": true,
            "type": "math"
        }
    },
    "{'number': '302127', 'fragment': 'true'}": {
        "error": "",
        "response": {
            "text": "a boring number",
            "number": 302127,
            "found": false,
            "type": "math"
        }
    },
    "{'number': '111'}": {
        "error": "",
        "response": {
            "text": "a perfect totient number",
            "number": 111,
            "found": true,
            "type": "math"
        }
    },
    "{'number': '789', 'fragment': 'true'}": {
        "error": "",
        "response": {
            "text": "an uninteresting number",
            "number": 789,
            "found": false,
            "type": "math"
        }
    },
    "{'number': '777', 'fragment': 'true'}": {
        "error": "",
        "response": {
            "text": "a repdigit in base 6 and in base 10",
            "number": 777,
            "found": true,
            "type": "math"
        }
    },
    "{'number': '321', 'json': 'true'}": {
        "error": "",
        "response": {
            "text": "an uninteresting number",
            "number": 321,
            "found": false,
            "type": "math"
        }
    },
    "{'number': '321', 'fragment': 'true'}": {
        "error": "",
        "response": {
            "text": "an uninteresting number",
            "number": 321,
            "found": false,
            "type": "math"
        }
    },
    "{'number': '123', 'json': 'true'}": {
        "error": "",
        "response": {
            "text": "the 10^{th} Lucas number",
            "number": 123,
            "found": true,
            "type": "math"
        }
    },
    "{'number': '888', 'fragment': 'true'}": {
        "error": "",
        "response": {
            "text": "an unremarkable number",
            "number": 888,
            "found": false,
            "type": "math"
        }
    },
    "{'number': '999', 'fragment': 'true'}": {
        "error": "",
        "response": {
            "text": "an uninteresting number",
            "number": 999,
            "found": false,
            "type": "math"
        }
    },
    "{'number': '313'}": {
        "error": "",
        "response": {
            "text": "the number of intersections when all the diagonals of a regular dodecagon are drawn",
            "number": 313,
            "found": true,
            "type": "math"
        }
    },
    "{'number': '1788', 'json': 'true'}": {
        "error": "",
        "response": {
            "text": "an uninteresting number",
            "number": 1788,
            "found": false,
            "type": "math"
        }
    },
    "{'number': '246'}": {
        "error": "",
        "response": {
            "text": "_{9}C_{2} + _{9}C_{4} + _{9}C_{6}",
            "number": 246,
            "found": true,
            "type": "math"
        }
    },
    "{'number': '284'}": {
        "error": "",
        "response": {
            "text": "an uninteresting number",
            "number": 284,
            "found": false,
            "type": "math"
        }
    },
    "{'number': '21', 'json': 'true'}": {
        "error": "",
        "response": {
            "text": "the fifth discrete Semiprime and the second in the (3.q) family",
            "number": 21,
            "found": true,
            "type": "math"
        }
    },
    "{'number': '384'}": {
        "error": "",
        "response": {
            "text": "a number for which we're missing a fact (submit one to numbersapi at google mail!)",
            "number": 384,
            "found": false,
            "type": "math"
        }
    },
    "{'number': '1844'}": {
        "error": "",
        "response": {
            "text": "an uninteresting number",
            "number": 1844,
            "found": false,
            "type": "math"
        }
    },
    "{'number': '96'}": {
        "error": "",
        "response": {
            "text": "the fourth Granville number and the second non-perfect Granville number",
            "number": 96,
            "found": true,
            "type": "math"
        }
    },
    "{'number': '1957', 'fragment': 'true'}": {
        "error": "",
        "response": {
            "text": "the number of permutations of some subset of 6 elements",
            "number": 1957,
            "found": true,
            "type": "math"
        }
    },
    "{'number': '5678', 'json': 'true'}": {
        "error": "",
        "response": {
            "text": "an unremarkable number",
            "number": 5678,
            "found": false,
            "type": "math"
        }
    },
    "{'number': '9876', 'json': 'true'}": {
        "error": "",
        "response": {
            "text": "the largest 4-digit number with different digits",
            "number": 9876,
            "found": true,
            "type": "math"
        }
    },
    "{'number': '999', 'json': 'true'}": {
        "error": "",
        "response": {
            "text": "an unremarkable number",
            "number": 999,
            "found": false,
            "type": "math"
        }
    },
    "{'number': '1001'}": {
        "error": "",
        "response": {
            "text": "the smallest palindromic product of 3 consecutive primes",
            "number": 1001,
            "found": true,
            "type": "math"
        }
    },
    "{'number': '296'}": {
        "error": "",
        "response": {
            "text": "the number of partitions of 30 into distinct parts",
            "number": 296,
            "found": true,
            "type": "math"
        }
    },
    "{'number': '1337'}": {
        "error": "",
        "response": {
            "text": "a number for which we're missing a fact (submit one to numbersapi at google mail!)",
            "number": 1337,
            "found": false,
            "type": "math"
        }
    },
    "{'number': '69', 'json': 'true'}": {
        "error": "",
        "response": {
            "text": "a value of n where n^{2} and n^{3} together contain each digit once",
            "number": 69,
            "found": true,
            "type": "math"
        }
    },
    "{'number': '173', 'json': 'true'}": {
        "error": "",
        "response": {
            "text": "an Eisenstein prime with no imaginary part",
            "number": 173,
            "found": true,
            "type": "math"
        }
    },
    "{'number': '800', 'json': 'true'}": {
        "error": "",
        "response": {
            "text": "a boring number",
            "number": 800,
            "found": false,
            "type": "math"
        }
    },
    "{'number': '1986', 'json': 'true'}": {
        "error": "",
        "response": {
            "text": "an uninteresting number",
            "number": 1986,
            "found": false,
            "type": "math"
        }
    },
    "{'number': '25', 'json': 'true'}": {
        "error": "",
        "response": {
            "text": "also a Cullen number",
            "number": 25,
            "found": true,
            "type": "math"
        }
    },
    "{'number': '50', 'json': 'true'}": {
        "error": "",
        "response": {
            "text": "the smallest number that can be written as the sum of of 2 squares in 2 ways",
            "number": 50,
            "found": true,
            "type": "math"
        }
    },
    "{'number': '1562'}": {
        "error": "",
        "response": {
            "text": "a boring number",
            "number": 1562,
            "found": false,
            "type": "math"
        }
    },
    "{'number': '172'}": {
        "error": "",
        "response": {
            "text": "a noncototient integer",
            "number": 172,
            "found": true,
            "type": "math"
        }
    },
    "{'number': '289'}": {
        "error": "",
        "response": {
            "text": "an unremarkable number",
            "number": 289,
            "found": false,
            "type": "math"
        }
    },
    "{'number': '1859'}": {
        "error": "",
        "response": {
            "text": "a boring number",
            "number": 1859,
            "found": false,
            "type": "math"
        }
    },
    "{'number': '957'}": {
        "error": "",
        "response": {
            "text": "a value of n for which s(n) = s(n+1)",
            "number": 957,
            "found": true,
            "type": "math"
        }
    },
    "{'number': '0.9163199999999999', 'json': 'true'}": {
        "error": "",
        "response": "Invalid url"
    },
    "{'number': '0.9163199999999999'}": {
        "error": "",
        "response": "Invalid url"
    },
    "{'number': '82', 'json': 'true'}": {
        "error": "",
        "response": {
            "text": "a companion Pell number",
            "number": 82,
            "found": true,
            "type": "math"
        }
    },
    "{'number': '857611'}": {
        "error": "",
        "response": {
            "text": "an unremarkable number",
            "number": 857611,
            "found": false,
            "type": "math"
        }
    },
    "{'number': '1975'}": {
        "error": "",
        "response": {
            "text": "a boring number",
            "number": 1975,
            "found": false,
            "type": "math"
        }
    },
    "{'number': '9160499999999999'}": {
        "error": "",
        "response": {
            "text": "a number for which we're missing a fact (submit one to numbersapi at google mail!)",
            "number": 9160500000000000,
            "found": false,
            "type": "math"
        }
    },
    "{'number': '2', 'fragment': 'true'}": {
        "error": "",
        "response": {
            "text": "a primorial, as well as its own factorial",
            "number": 2,
            "found": true,
            "type": "math"
        }
    },
    "{'number': '13', 'fragment': 'true'}": {
        "error": "",
        "response": {
            "text": "the number of Archimedian solids",
            "number": 13,
            "found": true,
            "type": "math"
        }
    },
    "{'number': '420'}": {
        "error": "",
        "response": {
            "text": "the smallest number divisible by 1 through 7",
            "number": 420,
            "found": true,
            "type": "math"
        }
    },
    "{'number': '657'}": {
        "error": "",
        "response": {
            "text": "the number of ways to tile a 4×22 rectangle with 4×1 rectangles",
            "number": 657,
            "found": true,
            "type": "math"
        }
    },
    "{'number': '158'}": {
        "error": "",
        "response": {
            "text": "the number of planar partitions of 11",
            "number": 158,
            "found": true,
            "type": "math"
        }
    },
    "{'number': '1727'}": {
        "error": "",
        "response": {
            "text": "a boring number",
            "number": 1727,
            "found": false,
            "type": "math"
        }
    },
    "{'number': '1726'}": {
        "error": "",
        "response": {
            "text": "an unremarkable number",
            "number": 1726,
            "found": false,
            "type": "math"
        }
    },
    "{'number': '100', 'fragment': 'true'}": {
        "error": "",
        "response": {
            "text": "the square of 10 (in scientific notation it is written as 102)",
            "number": 100,
            "found": true,
            "type": "math"
        }
    },
    "{'number': '1234', 'fragment': 'true'}": {
        "error": "",
        "response": {
            "text": "the smallest 4-digit number with increasing digits",
            "number": 1234,
            "found": true,
            "type": "math"
        }
    },
    "{'number': '2468', 'fragment': 'true'}": {
        "error": "",
        "response": {
            "text": "a number for which we're missing a fact (submit one to numbersapi at google mail!)",
            "number": 2468,
            "found": false,
            "type": "math"
        }
    },
    "{'number': '365', 'fragment': 'true'}": {
        "error": "",
        "response": {
            "text": "the smallest number that can be written as a sum of consecutive squares in more than 1 way",
            "number": 365,
            "found": true,
            "type": "math"
        }
    },
    "{'number': '55', 'fragment': 'true'}": {
        "error": "",
        "response": {
            "text": "a semiprime, being the product of 5 and 11 and it is the 2nd member of the (5.q) semiprime family",
            "number": 55,
            "found": true,
            "type": "math"
        }
    },
    "{'number': '67', 'fragment': 'true'}": {
        "error": "",
        "response": {
            "text": "the smallest number which is palindromic in bases 5 and 6",
            "number": 67,
            "found": true,
            "type": "math"
        }
    },
    "{'number': '4500'}": {
        "error": "",
        "response": {
            "text": "the number of regions formed when all diagonals are drawn in a regular 20-gon",
            "number": 4500,
            "found": true,
            "type": "math"
        }
    },
    "{'number': '450'}": {
        "error": "",
        "response": {
            "text": "the number of 13-iamonds with holes",
            "number": 450,
            "found": true,
            "type": "math"
        }
    },
    "{'number': '616'}": {
        "error": "",
        "response": {
            "text": "a boring number",
            "number": 616,
            "found": false,
            "type": "math"
        }
    },
    "{'number': '2460', 'fragment': 'true'}": {
        "error": "",
        "response": {
            "text": "a number for which we're missing a fact (submit one to numbersapi at google mail!)",
            "number": 2460,
            "found": false,
            "type": "math"
        }
    },
    "{'number': '2461', 'fragment': 'true'}": {
        "error": "",
        "response": {
            "text": "an uninteresting number",
            "number": 2461,
            "found": false,
            "type": "math"
        }
    },
    "{'number': '11'}": {
        "error": "",
        "response": {
            "text": "a Størmer number, a Heegner number, and a Mills prime",
            "number": 11,
            "found": true,
            "type": "math"
        }
    },
    "{'number': '1', 'fragment': 'true'}": {
        "error": "",
        "response": {
            "text": "also the first and second numbers in the Fibonacci sequence and is the first number in many other mathematical sequences",
            "number": 1,
            "found": true,
            "type": "math"
        }
    },
    "{'number': '10', 'fragment': 'true'}": {
        "error": "",
        "response": {
            "text": "the second discrete semiprime (2.5) and the second member of the (2.q) discrete semiprime family",
            "number": 10,
            "found": true,
            "type": "math"
        }
    },
    "{'number': '128'}": {
        "error": "",
        "response": {
            "text": "the seventh power of 2",
            "number": 128,
            "found": true,
            "type": "math"
        }
    },
    "{'number': '1960'}": {
        "error": "",
        "response": {
            "text": "the Stirling number of the first kind s(8,5)",
            "number": 1960,
            "found": true,
            "type": "math"
        }
    },
    "{'number': '1610612747'}": {
        "error": "",
        "response": {
            "text": "an uninteresting number",
            "number": 1610612747,
            "found": false,
            "type": "math"
        }
    },
    "{'number': '135', 'json': 'true'}": {
        "error": "",
        "response": {
            "text": "1^{1} + 3^{2} + 5^{3}",
            "number": 135,
            "found": true,
            "type": "math"
        }
    },
    "{'number': '450', 'fragment': 'true'}": {
        "error": "",
        "response": {
            "text": "the number of 13-iamonds with holes",
            "number": 450,
            "found": true,
            "type": "math"
        }
    },
    "{'number': '51', 'json': 'true'}": {
        "error": "",
        "response": {
            "text": "the 6^{th} Motzkin number",
            "number": 51,
            "found": true,
            "type": "math"
        }
    },
    "{'number': '0.7869988'}": {
        "error": "",
        "response": "Invalid url"
    },
    "{'number': '192', 'json': 'true'}": {
        "error": "",
        "response": {
            "text": "the smallest number with 14 divisors",
            "number": 192,
            "found": true,
            "type": "math"
        }
    },
    "{'number': '1', 'json': 'true'}": {
        "error": "",
        "response": {
            "text": "the first figurate number of every kind, such as triangular number, pentagonal number and centered hexagonal number, to name just a few",
            "number": 1,
            "found": true,
            "type": "math"
        }
    },
    "{'number': '2', 'json': 'true'}": {
        "error": "",
        "response": {
            "text": "many properties in mathematics",
            "number": 2,
            "found": true,
            "type": "math"
        }
    },
    "{'number': '9', 'json': 'true'}": {
        "error": "",
        "response": {
            "text": "this works regardless of the number of digits that are transposed",
            "number": 9,
            "found": true,
            "type": "math"
        }
    },
    "{'number': '20', 'json': 'true'}": {
        "error": "",
        "response": {
            "text": "the number of quarter or half turns required to optimally solve a Rubik's cube in the worst case",
            "number": 20,
            "found": true,
            "type": "math"
        }
    },
    "{'number': '365', 'json': 'true'}": {
        "error": "",
        "response": {
            "text": "the smallest number that can be written as a sum of consecutive squares in more than 1 way",
            "number": 365,
            "found": true,
            "type": "math"
        }
    },
    "{'number': '27', 'fragment': 'true'}": {
        "error": "",
        "response": {
            "text": "a perfect cube, being 33 = 3 × 3 × 3",
            "number": 27,
            "found": true,
            "type": "math"
        }
    },
    "{'number': '83'}": {
        "error": "",
        "response": {
            "text": "also a highly cototient number",
            "number": 83,
            "found": true,
            "type": "math"
        }
    },
    "{'number': '620', 'json': 'true'}": {
        "error": "",
        "response": {
            "text": "the number of sided 7-hexes",
            "number": 620,
            "found": true,
            "type": "math"
        }
    },
    "{'number': '3', 'fragment': 'true'}": {
        "error": "",
        "response": {
            "text": "the first unique prime due to the properties of its reciprocal",
            "number": 3,
            "found": true,
            "type": "math"
        }
    },
    "{'number': '33'}": {
        "error": "",
        "response": {
            "text": "the largest number that is not a sum of distinct triangular numbers",
            "number": 33,
            "found": true,
            "type": "math"
        }
    },
    "{'number': '100', 'json': 'true'}": {
        "error": "",
        "response": {
            "text": "the square of 10 (in scientific notation it is written as 102)",
            "number": 100,
            "found": true,
            "type": "math"
        }
    },
    "{'number': '1980'}": {
        "error": "",
        "response": {
            "text": "the number of ways to fold a 2×4 rectangle of stamps",
            "number": 1980,
            "found": true,
            "type": "math"
        }
    },
    "{'number': '1006', 'fragment': 'true'}": {
        "error": "",
        "response": {
            "text": "a boring number",
            "number": 1006,
            "found": false,
            "type": "math"
        }
    },
    "{'number': '27', 'json': 'true'}": {
        "error": "",
        "response": {
            "text": "a perfect cube, being 33 = 3 × 3 × 3",
            "number": 27,
            "found": true,
            "type": "math"
        }
    },
    "{'number': '136', 'fragment': 'true'}": {
        "error": "",
        "response": {
            "text": "the sum of the first 16 positive integers",
            "number": 136,
            "found": true,
            "type": "math"
        }
    },
    "{'number': '136', 'json': 'true'}": {
        "error": "",
        "response": {
            "text": "the sum of the first 16 positive integers",
            "number": 136,
            "found": true,
            "type": "math"
        }
    },
    "{'number': '1357'}": {
        "error": "",
        "response": {
            "text": "a boring number",
            "number": 1357,
            "found": false,
            "type": "math"
        }
    },
    "{'number': '144'}": {
        "error": "",
        "response": {
            "text": "the smallest number with exactly 15 divisors",
            "number": 144,
            "found": true,
            "type": "math"
        }
    },
    "{'number': '90'}": {
        "error": "",
        "response": {
            "text": "the number of degrees in a right angle",
            "number": 90,
            "found": true,
            "type": "math"
        }
    },
    "{'number': '167'}": {
        "error": "",
        "response": {
            "text": "a Gaussian prime number",
            "number": 167,
            "found": true,
            "type": "math"
        }
    },
    "{'number': '62'}": {
        "error": "",
        "response": {
            "text": "the smallest number that can be written as the sum of of 3 distinct squares in 2 ways",
            "number": 62,
            "found": true,
            "type": "math"
        }
    },
    "{'number': '187'}": {
        "error": "",
        "response": {
            "text": "a centered 31-gonal number",
            "number": 187,
            "found": true,
            "type": "math"
        }
    },
    "{'number': '233'}": {
        "error": "",
        "response": {
            "text": "an irregular prime, a full reptend prime, a cousin prime, a Chen prime, a Fibonacci prime and a sexy prime",
            "number": 233,
            "found": true,
            "type": "math"
        }
    },
    "{'number': '2', 'fragment': 'true', 'json': 'true'}": {
        "error": "",
        "response": {
            "text": "the smallest and the first prime number, and the only even one (for this reason it is sometimes called \"the oddest prime\")",
            "number": 2,
            "found": true,
            "type": "math"
        }
    },
    "{'number': '5', 'fragment': 'true', 'json': 'true'}": {
        "error": "",
        "response": {
            "text": "the second Sierpinski number of the first kind, and can be written as S2=(22)+1",
            "number": 5,
            "found": true,
            "type": "math"
        }
    },
    "{'number': '10', 'fragment': 'true', 'json': 'true'}": {
        "error": "",
        "response": {
            "text": "the number of n-Queens Problem solutions for n = 5",
            "number": 10,
            "found": true,
            "type": "math"
        }
    },
    "{'number': '1729', 'fragment': 'math', 'json': 'string'}": {
        "error": "",
        "response": {
            "text": "the smallest natural number representable in two different ways as a sum of two positive cubes, as Ramanujan stated on the spot",
            "number": 1729,
            "found": true,
            "type": "math"
        }
    },
    "{'number': '1', 'fragment': 'trivia', 'json': 'true'}": {
        "error": "",
        "response": {
            "text": "the first figurate number of every kind, such as triangular number, pentagonal number and centered hexagonal number, to name just a few",
            "number": 1,
            "found": true,
            "type": "math"
        }
    },
    "{'number': 1, 'fragment': 'trivia', 'json': 'true'}": {
        "error": "",
        "response": {
            "text": "the first figurate number of every kind, such as triangular number, pentagonal number and centered hexagonal number, to name just a few",
            "number": 1,
            "found": true,
            "type": "math"
        }
    },
    "{'number': '1729', 'json': 'true', 'fragment': 'true'}": {
        "error": "",
        "response": {
            "text": "the smallest natural number representable in two different ways as a sum of two positive cubes, as Ramanujan stated on the spot",
            "number": 1729,
            "found": true,
            "type": "math"
        }
    },
    "{'number': '52'}": {
        "error": "",
        "response": {
            "text": "the 5^{th} Bell number",
            "number": 52,
            "found": true,
            "type": "math"
        }
    }
}